{"Aatrox": "top", "Ahri": "middle", "Akali": "middle", "Akshan": "middle", "Alistar": "support", "Amumu": "jungle", "Anivia": "middle", "Annie": "middle", "Aphelios": "bottom", "Ashe": "bottom", "AurelionSol": "middle", "Azir": "middle", "Bard": "support", "Belveth":"jungle","Blitzcrank": "support", "Brand": "support", "Braum": "support", "Caitlyn": "bottom", "Camille": "top", "Cassiopeia": "middle", "Chogath": "top", "Corki": "middle", "Darius": "top", "Diana": "jungle", "Draven": "bottom", "DrMundo": "top", "Ekko": "jungle", "Elise": "jungle", "Evelynn": "jungle", "Ezreal": "bottom", "Fiddlesticks": "jungle", "Fiora": "top", "Fizz": "middle", "Galio": "middle", "Gangplank": "top", "Garen": "top", "Gnar": "top", "Gragas": "top", "Graves": "jungle", "Gwen": "top", "Hecarim": "jungle", "Heimerdinger": "middle", "Illaoi": "top", "Irelia": "top", "Ivern": "jungle", "Janna": "support", "JarvanIV": "jungle", "Jax": "top", "Jayce": "top", "Jhin": "bottom", "Jinx": "bottom", "Kaisa": "bottom", "Kalista": "bottom", "Karma": "support", "Karthus": "jungle", "Kassadin": "middle", "Katarina": "middle", "Kayle": "top", "Kayn": "jungle", "Kennen": "top", "Khazix": "jungle", "Kindred": "jungle", "Kled": "top", "KogMaw": "bottom", "Leblanc": "middle", "LeeSin": "jungle", "Leona": "support", "Lillia": "jungle", "Lissandra": "middle", "Lucian": "bottom", "Lulu": "support", "Lux": "support", "Malphite": "top", "Malzahar": "middle", "Maokai": "support", "MasterYi": "jungle", "MissFortune": "bottom", "MonkeyKing": "jungle", "Mordekaiser": "top", "Morgana": "support", "Nami": "support", "Nasus": "top", "Nautilus": "support", "Neeko": "middle", "Nidalee": "jungle", "Nocturne": "jungle", "Nunu": "jungle", "Olaf": "top", "Orianna": "middle", "Ornn": "top", "Pantheon": "support", "Poppy": "jungle", "Pyke": "support", "Qiyana": "middle", "Quinn": "top", "Rakan": "support", "Rammus": "jungle", "RekSai": "jungle", "Rell": "support", "Renata": "support", "Renekton": "top", "Rengar": "jungle", "Riven": "top", "Rumble": "top", "Ryze": "middle", "Samira": "bottom", "Sejuani": "jungle", "Senna": "support", "Seraphine": "support", "Sett": "top", "Shaco": "jungle", "Shen": "top", "Shyvana": "jungle", "Singed": "top", "Sion": "top", "Sivir": "bottom", "Skarner": "jungle", "Sona": "support", "Soraka": "support", "Swain": "support", "Sylas": "middle", "Syndra": "middle", "TahmKench": "top", "Taliyah": "middle", "Talon": "jungle", "Taric": "support", "Teemo": "top", "Thresh": "support", "Tristana": "bottom", "Trundle": "jungle", "Tryndamere": "top", "TwistedFate": "middle", "Twitch": "bottom", "Udyr": "jungle", "Urgot": "top", "Varus": "bottom", "Vayne": "bottom", "Veigar": "middle", "Velkoz": "support", "Vex": "middle", "Vi": "jungle", "Viego": "jungle", "Viktor": "middle", "Vladimir": "middle", "Volibear": "jungle", "Warwick": "jungle", "Xayah": "bottom", "Xerath": "support", "XinZhao": "jungle", "Yasuo": "middle", "Yone": "middle", "Yorick": "top", "Yuumi": "support", "Zac": "jungle", "Zed": "middle", "Zeri": "bottom", "Ziggs": "bottom", "Zilean": "support", "Zoe": "middle", "Zyra": "support"}